release_tools/__init__.py
release_tools/_version.py
release_tools/changelog.py
release_tools/entry.py
release_tools/notes.py
release_tools/project.py
release_tools/publish.py
release_tools/repo.py
release_tools/semverup.py
release_tools-0.6.0.dist-info/LICENSE
release_tools-0.6.0.dist-info/METADATA
release_tools-0.6.0.dist-info/WHEEL
release_tools-0.6.0.dist-info/entry_points.txt
release_tools-0.6.0.dist-info/RECORD
