Metadata-Version: 2.1
Name: release-tools
Version: 0.6.0
Summary: Set of tools to generate Python releases.
License: GPL-3.0-or-later
Keywords: development,build
Author: Santiago Dueñas
Author-email: sduenas@bitergia.com
Requires-Python: >=3.8,<4.0
Classifier: Development Status :: 4 - Beta
Classifier: Intended Audience :: Developers
Classifier: License :: OSI Approved :: GNU General Public License v3 or later (GPLv3+)
Classifier: Programming Language :: Python :: 3
Classifier: Programming Language :: Python :: 3.8
Classifier: Programming Language :: Python :: 3.9
Classifier: Programming Language :: Python :: 3.10
Classifier: Programming Language :: Python :: 3.11
Classifier: Topic :: Software Development :: Build Tools
Requires-Dist: PyYAML (>=6.0.1,<7.0.0)
Requires-Dist: click (>=7.0,<8.0)
Requires-Dist: semver (>=2.9,<3.0)
Requires-Dist: tomlkit (>=0.5.8,<0.6.0)
